{
  "commitMessage": "vault backup: {{date}} {{hostname}} {{numFiles}}",
  "autoCommitMessage": "vault backup: {{date}} {{hostname}} {{numFiles}}",
  "commitDateFormat": "YYYY-MM-DD HH:mm:ss",
  "autoSaveInterval": 1,
  "autoPullInterval": 5,
  "autoPullOnBoot": true,
  "disablePush": false,
  "pullBeforePush": true,
  "disablePopups": false,
  "listChangedFilesInMessageBody": true,
  "showStatusBar": true,
  "updateSubmodules": false,
  "syncMethod": "merge",
  "gitPath": "",
  "customMessageOnAutoBackup": false,
  "autoBackupAfterFileChange": true,
  "treeStructure": false,
  "refreshSourceControl": true
}